appcfg/__init__.py
appcfg/appcfg.py
appcfg/exceptions.py
appcfg/util.py
appcfg-1.1.1.dist-info/WHEEL
appcfg-1.1.1.dist-info/METADATA
appcfg-1.1.1.dist-info/RECORD
