Metadata-Version: 2.1
Name: appcfg
Version: 1.1.1
Summary: Flexible hierarchic Python application configuration
Home-page: https://github.com/bjoluc/appcfg
License: MIT
Keywords: app,application,config,configuration,env,environment,node-config
Author: bjoluc
Author-email: mail@bjoluc.de
Requires-Python: >=3.6,<4.0
Classifier: Development Status :: 5 - Production/Stable
Classifier: Intended Audience :: Developers
Classifier: License :: OSI Approved :: MIT License
Classifier: Operating System :: OS Independent
Classifier: Programming Language :: Python :: 3
Classifier: Programming Language :: Python :: 3.6
Classifier: Programming Language :: Python :: 3.7
Classifier: Programming Language :: Python :: 3.8
Classifier: Programming Language :: Python :: Implementation :: CPython
Classifier: Topic :: Software Development :: Libraries
Classifier: Typing :: Typed
Provides-Extra: yaml
Requires-Dist: deepmerge (>=0.1.0,<0.2.0)
Requires-Dist: pyyaml (>=5.3.1,<6.0.0); extra == "yaml"
Project-URL: Documentation, https://github.com/bjoluc/appcfg#readme
Project-URL: Repository, https://github.com/bjoluc/appcfg
